orcid_scraping/__init__.py
orcid_scraping/errors.py
orcid_scraping/logger.py
orcid_scraping/utils.py
orcid_scraping/models/__init__.py
orcid_scraping/models/orcid.py
orcid_scraping/models/scrape_result.py
orcid_scraping/models/researcher/__init__.py
orcid_scraping/models/researcher/work.py
orcid_scraping/models/researcher/work_url.py
orcid_scraping/tools/__init__.py
orcid_scraping/tools/base.py
orcid_scraping/tools/api/__init__.py
orcid_scraping/tools/api/models.py
orcid_scraping/tools/api/tool.py
orcid_scraping/tools/selenium/__init__.py
orcid_scraping/tools/selenium/models.py
orcid_scraping/tools/selenium/tool.py
orcid_scraping-0.1.0.dist-info/METADATA
orcid_scraping-0.1.0.dist-info/WHEEL
orcid_scraping-0.1.0.dist-info/licenses/LICENSE
orcid_scraping-0.1.0.dist-info/RECORD
